{
  "name": "ubuntu",
  "description": "Sets up sources for ubuntu",
  "long_description": "",
  "maintainer": "Opscode, Inc.",
  "maintainer_email": "cookbooks@opscode.com",
  "license": "Apache 2.0",
  "platforms": {
    "ubuntu": [

    ]
  },
  "dependencies": {
    "apt": [

    ]
  },
  "recommendations": {
  },
  "suggestions": {
  },
  "conflicting": {
  },
  "providing": {
  },
  "replacing": {
  },
  "attributes": {
  },
  "groupings": {
  },
  "recipes": {
    "ubuntu": "Sets up sources for the node's ubuntu release"
  },
  "version": "0.8.1"
}