{
  "version": "0.9.1",
  "providing": {

  },
  "attributes": {

  },
  "maintainer": "Opscode, Inc.",
  "replacing": {

  },
  "dependencies": {

  },
  "long_description": "",
  "maintainer_email": "cookbooks@opscode.com",
  "groupings": {

  },
  "recipes": {
    "iptables": "Installs iptables and sets up .d style config directory of iptables rules"
  },
  "recommendations": {

  },
  "license": "Apache 2.0",
  "suggestions": {

  },
  "name": "iptables",
  "conflicting": {

  },
  "platforms": {
    "debian": [

    ],
    "centos": [

    ],
    "ubuntu": [

    ],
    "redhat": [

    ]
  },
  "description": "Sets up iptables to use a script to maintain rules"
}